FinanceLib/__init__.py
FinanceLib/analysis.py
FinanceLib/genBanking.py
FinanceLib/interest.py
FinanceLib-0.0.2.dist-info/LICENSE
FinanceLib-0.0.2.dist-info/METADATA
FinanceLib-0.0.2.dist-info/WHEEL
FinanceLib-0.0.2.dist-info/top_level.txt
FinanceLib-0.0.2.dist-info/RECORD
