Metadata-Version: 2.1
Name: FinanceLib
Version: 0.0.2
Summary: A python library that consists of modules for different types of financial calculations and analysis.
Home-page: https://github.com/sris-spec/FinanceLib.git
Author: Chahat Mittal,Harleen Kaur,Sristhi Sahoo
Author-email: financeLib027@gmail.com
License: MIT
Keywords: python,Finance with python,interest,analysis,general banking,visualising finance,stock,yahoo finance
Platform: UNKNOWN
Classifier: Intended Audience :: Developers
Classifier: Programming Language :: Python :: 3
Classifier: Operating System :: Unix
Classifier: Operating System :: MacOS :: MacOS X
Classifier: Operating System :: Microsoft :: Windows
Classifier: License :: OSI Approved :: MIT License
Requires-Python: >=3.7
License-File: LICENSE
Requires-Dist: matplotlib
Requires-Dist: numpy
Requires-Dist: pandas-datareader
Requires-Dist: pandas
Requires-Dist: mypy
